RISC_V.srcs/sources_1/new/data_memory.v
// File: data_memory.v
// Data Memory Module
`timescale 1ns / 1ps

module data_memory (
    input clk,
    input [31:0] addr,
    input [31:0] write_data,
    input mem_write,
    input mem_read,
    output reg [31:0] read_data
);
    reg [31:0] memory [0:255]; // 256 words

    always @(posedge clk) begin
        if (mem_write)
            memory[addr[9:2]] <= write_data;
    end

    always @(*) begin
        if (mem_read)
            read_data = memory[addr[9:2]];
        else
            read_data = 32'b0;
    end

    // Initialize data memory if needed
    integer i;
    initial begin
        for (i = 0; i < 256; i = i + 1)
            memory[i] = 32'b0;
    end
endmodule

RISC_V.srcs/sources_1/new/alu.v
// File: alu.v
// ALU Module
`timescale 1ns / 1ps

module alu (
    input [31:0] operand_a,
    input [31:0] operand_b,
    input [3:0] alu_control,
    output reg [31:0] alu_result,
    output zero
);
    assign zero = (alu_result == 0);

    always @(*) begin
        case (alu_control)
            4'b0000: alu_result = operand_a & operand_b;             // AND
            4'b0001: alu_result = operand_a | operand_b;             // OR
            4'b0010: alu_result = operand_a + operand_b;             // ADD
            4'b0110: alu_result = operand_a - operand_b;             // SUB
            4'b0111: alu_result = (operand_a < operand_b) ? 1 : 0;   // SLT
            4'b1100: alu_result = ~(operand_a | operand_b);          // NOR
            default: alu_result = 0;
        endcase
    end
endmodule

RISC_V.srcs/sources_1/new/alu_control.v
// File: alu_control.v
// ALU Control Unit Module
`timescale 1ns / 1ps

module alu_control (
    input [1:0] alu_op,
    input [2:0] funct3,
    input [6:0] funct7,
    output reg [3:0] alu_control
);
    always @(*) begin
        case (alu_op)
            2'b00: alu_control = 4'b0010; // ADD for Load/Store/ADDI
            2'b01: alu_control = 4'b0110; // SUB for BEQ
            2'b10: begin // R-type instructions
                if (funct7 == 7'b0000000) begin
                    case (funct3)
                        3'b000: alu_control = 4'b0010; // ADD
                        3'b111: alu_control = 4'b0000; // AND
                        3'b110: alu_control = 4'b0001; // OR
                        default: alu_control = 4'b0000;
                    endcase
                end else if (funct7 == 7'b0100000 && funct3 == 3'b000) begin
                    alu_control = 4'b0110; // SUB
                end else begin
                    alu_control = 4'b0000;
                end
            end
            default: alu_control = 4'b0000;
        endcase
    end
endmodule

RISC_V.srcs/sources_1/new/sign_extender.v
// File: sign_extender.v
// Sign Extender Module
`timescale 1ns / 1ps

module sign_extender (
    input [31:0] instruction,
    output reg [31:0] immediate
);
    always @(*) begin
        case (instruction[6:0])
            7'b0000011, // Load
            7'b0010011: // Immediate arithmetic
                immediate = {{20{instruction[31]}}, instruction[31:20]};
            7'b0100011: // Store
                immediate = {{20{instruction[31]}}, instruction[31:25], instruction[11:7]};
            7'b1100011: // Branch
                immediate = {{19{instruction[31]}}, instruction[31], instruction[7],
                             instruction[30:25], instruction[11:8], 1'b0};
            default:
                immediate = 32'b0;
        endcase
    end
endmodule

RISC_V.srcs/sources_1/new/register_file.v
// File: register_file.v
// Register File Module
`timescale 1ns / 1ps

module register_file (
    input clk,
    input [4:0] rs1_addr,
    input [4:0] rs2_addr,
    input [4:0] rd_addr,
    input [31:0] rd_data,
    input reg_write,
    output [31:0] rs1_data,
    output [31:0] rs2_data
);
    reg [31:0] registers [0:31];

    // Read operations
    assign rs1_data = registers[rs1_addr];
    assign rs2_data = registers[rs2_addr];

    // Write operation
    always @(posedge clk) begin
        if (reg_write && rd_addr != 0)
            registers[rd_addr] <= rd_data;
    end

    // Initialize registers
    integer i;
    initial begin
        for (i = 0; i < 32; i = i + 1)
            registers[i] = 32'b0;
    end
endmodule

RISC_V.srcs/sources_1/new/control_unit.v
// File: control_unit.v
// Control Unit Module
`timescale 1ns / 1ps

module control_unit (
    input [6:0] opcode,
    output reg reg_write,
    output reg mem_to_reg,
    output reg mem_read,
    output reg mem_write,
    output reg branch,
    output reg [1:0] alu_op,
    output reg alu_src
);
    always @(*) begin
        case (opcode)
            7'b0110011: begin // R-type
                reg_write = 1;
                mem_to_reg = 0;
                mem_read = 0;
                mem_write = 0;
                branch = 0;
                alu_op = 2'b10;
                alu_src = 0;
            end
            7'b0000011: begin // Load (LW)
                reg_write = 1;
                mem_to_reg = 1;
                mem_read = 1;
                mem_write = 0;
                branch = 0;
                alu_op = 2'b00;
                alu_src = 1;
            end
            7'b0100011: begin // Store (SW)
                reg_write = 0;
                mem_to_reg = 0;
                mem_read = 0;
                mem_write = 1;
                branch = 0;
                alu_op = 2'b00;
                alu_src = 1;
            end
            7'b1100011: begin // Branch (BEQ)
                reg_write = 0;
                mem_to_reg = 0;
                mem_read = 0;
                mem_write = 0;
                branch = 1;
                alu_op = 2'b01;
                alu_src = 0;
            end
            7'b0010011: begin // Immediate arithmetic (ADDI)
                reg_write = 1;
                mem_to_reg = 0;
                mem_read = 0;
                mem_write = 0;
                branch = 0;
                alu_op = 2'b00;
                alu_src = 1;
            end
            default: begin
                reg_write = 0;
                mem_to_reg = 0;
                mem_read = 0;
                mem_write = 0;
                branch = 0;
                alu_op = 2'b00;
                alu_src = 0;
            end
        endcase
    end
endmodule

RISC_V.srcs/sources_1/new/instruction_memory.v
// File: instruction_memory.v
// Instruction Memory Module with Corrected Test Program
`timescale 1ns / 1ps

module instruction_memory (
    input [31:0] addr,
    output [31:0] instruction
);
    reg [31:0] memory [0:255]; // 256 instructions

    integer i;
    reg signed [11:0] imm;     // 12-bit signed immediate
    reg [4:0] rd;              // 5-bit destination register
    reg [4:0] rs1;             // 5-bit source register 1
    reg [4:0] rs2;             // 5-bit source register 2
    reg [6:0] funct7;          // 7-bit funct7 field
    reg [2:0] funct3;          // 3-bit funct3 field
    reg [6:0] opcode;          // 7-bit opcode field
    reg [31:0] instruction_word;

    initial begin
        // Initialize instruction memory with a test program that writes to many registers

        // Program:
        // Initialize registers x1 to x31 with values 10, 20, ..., 310
        // Using ADDI instructions

        for (i = 0; i < 31; i = i + 1) begin
            rd = i + 1;
            rs1 = 5'd0; // x0
            funct3 = 3'b000; // For ADDI
            opcode = 7'b0010011; // Opcode for immediate arithmetic instructions

            // Calculate immediate value and ensure it fits in 12 bits
            imm = (i + 1) * 10;
            if (imm > 2047) begin
                imm = 2047; // Limit to maximum positive value
            end

            // Build the instruction word for ADDI
            instruction_word = {imm[11:0], rs1[4:0], funct3[2:0], rd[4:0], opcode[6:0]};
            memory[i] = instruction_word;
        end

        // Perform operations on the registers

        // ADD x31, x1, x2     ; x31 = x1 + x2
        funct7 = 7'b0000000;
        rs2 = 5'd2; // x2
        rs1 = 5'd1; // x1
        funct3 = 3'b000; // For ADD
        rd = 5'd31; // x31
        opcode = 7'b0110011; // Opcode for R-type instructions
        instruction_word = {funct7[6:0], rs2[4:0], rs1[4:0], funct3[2:0], rd[4:0], opcode[6:0]};
        memory[31] = instruction_word;

        // SUB x30, x3, x4     ; x30 = x3 - x4
        funct7 = 7'b0100000; // For SUB
        rs2 = 5'd4; // x4
        rs1 = 5'd3; // x3
        funct3 = 3'b000; // For SUB
        rd = 5'd30; // x30
        opcode = 7'b0110011;
        instruction_word = {funct7[6:0], rs2[4:0], rs1[4:0], funct3[2:0], rd[4:0], opcode[6:0]};
        memory[32] = instruction_word;

        // AND x29, x5, x6     ; x29 = x5 & x6
        funct7 = 7'b0000000;
        rs2 = 5'd6; // x6
        rs1 = 5'd5; // x5
        funct3 = 3'b111; // For AND
        rd = 5'd29; // x29
        opcode = 7'b0110011;
        instruction_word = {funct7[6:0], rs2[4:0], rs1[4:0], funct3[2:0], rd[4:0], opcode[6:0]};
        memory[33] = instruction_word;

        // OR x28, x7, x8      ; x28 = x7 | x8
        funct7 = 7'b0000000;
        rs2 = 5'd8; // x8
        rs1 = 5'd7; // x7
        funct3 = 3'b110; // For OR
        rd = 5'd28; // x28
        opcode = 7'b0110011;
        instruction_word = {funct7[6:0], rs2[4:0], rs1[4:0], funct3[2:0], rd[4:0], opcode[6:0]};
        memory[34] = instruction_word;

        // SLT x27, x9, x10    ; x27 = (x9 < x10) ? 1 : 0
        funct7 = 7'b0000000;
        rs2 = 5'd10; // x10
        rs1 = 5'd9; // x9
        funct3 = 3'b010; // For SLT
        rd = 5'd27; // x27
        opcode = 7'b0110011;
        instruction_word = {funct7[6:0], rs2[4:0], rs1[4:0], funct3[2:0], rd[4:0], opcode[6:0]};
        memory[35] = instruction_word;

        // Additional instructions can be added here
    end

    assign instruction = memory[addr[9:2]]; // Word-aligned address
endmodule

RISC_V.srcs/sources_1/new/pc.v
// File: pc.v
// Program Counter Module
`timescale 1ns / 1ps

module pc (
    input clk,
    input reset,
    input [31:0] pc_in,
    output reg [31:0] pc_out
);
    always @(posedge clk or posedge reset) begin
        if (reset)
            pc_out <= 32'b0;
        else
            pc_out <= pc_in;
    end
endmodule

RISC_V.srcs/sources_1/new/risc_v_processor.v
// File: risc_v_processor.v
// RISC-V Processor Top Module
`timescale 1ns / 1ps

module risc_v_processor (
    input clk,
    input reset
);
    wire [31:0] pc_in;
    wire [31:0] pc_out;
    wire [31:0] instruction;
    wire [31:0] rs1_data, rs2_data;
    wire [31:0] alu_result;
    wire [31:0] mem_read_data;
    wire [31:0] write_data;
    wire [31:0] immediate;
    wire zero;
    wire [6:0] opcode;
    wire [2:0] funct3;
    wire [6:0] funct7;
    wire [4:0] rs1_addr, rs2_addr, rd_addr;

    // Control signals
    wire reg_write, mem_to_reg, mem_read, mem_write, branch, alu_src;
    wire [1:0] alu_op;
    wire [3:0] alu_control;

    // Program Counter
    pc PC (
        .clk(clk),
        .reset(reset),
        .pc_in(pc_in),
        .pc_out(pc_out)
    );

    // Instruction Memory
    instruction_memory IMEM (
        .addr(pc_out),
        .instruction(instruction)
    );

    // Extract instruction fields
    assign opcode = instruction[6:0];
    assign rd_addr = instruction[11:7];
    assign funct3 = instruction[14:12];
    assign rs1_addr = instruction[19:15];
    assign rs2_addr = instruction[24:20];
    assign funct7 = instruction[31:25];

    // Control Unit
    control_unit CU (
        .opcode(opcode),
        .reg_write(reg_write),
        .mem_to_reg(mem_to_reg),
        .mem_read(mem_read),
        .mem_write(mem_write),
        .branch(branch),
        .alu_op(alu_op),
        .alu_src(alu_src)
    );

    // Register File
    register_file RF (
        .clk(clk),
        .rs1_addr(rs1_addr),
        .rs2_addr(rs2_addr),
        .rd_addr(rd_addr),
        .rd_data(write_data),
        .reg_write(reg_write),
        .rs1_data(rs1_data),
        .rs2_data(rs2_data)
    );

    // Sign Extender
    sign_extender SE (
        .instruction(instruction),
        .immediate(immediate)
    );

    // ALU Control Unit
    alu_control ALU_CU (
        .alu_op(alu_op),
        .funct3(funct3),
        .funct7(funct7),
        .alu_control(alu_control)
    );

    // ALU
    wire [31:0] alu_operand_b;
    assign alu_operand_b = (alu_src) ? immediate : rs2_data;
    alu ALU (
        .operand_a(rs1_data),
        .operand_b(alu_operand_b),
        .alu_control(alu_control),
        .alu_result(alu_result),
        .zero(zero)
    );

    // Data Memory
    data_memory DMEM (
        .clk(clk),
        .addr(alu_result),
        .write_data(rs2_data),
        .mem_write(mem_write),
        .mem_read(mem_read),
        .read_data(mem_read_data)
    );

    // Write back data selection
    assign write_data = (mem_to_reg) ? mem_read_data : alu_result;

    // Next PC computation
    wire [31:0] pc_plus_4;
    assign pc_plus_4 = pc_out + 4;
    wire [31:0] branch_target;
    assign branch_target = pc_out + immediate;

    assign pc_in = (branch && zero) ? branch_target : pc_plus_4;

endmodule

RISC_V.srcs/sim_1/new/risc_v_processor_tb.v
// File: risc_v_processor_tb.v
// Testbench for the RISC-V Processor with Extended Register Testing
`timescale 1ns / 1ps

module risc_v_processor_tb;
    reg clk;
    reg reset;

    // Instantiate the processor
    risc_v_processor uut (
        .clk(clk),
        .reset(reset)
    );

    // Clock generation
    initial begin
        clk = 0;
        forever #5 clk = ~clk; // 100MHz clock (Period = 10ns)
    end

    // Simulation control
    initial begin
        // Apply reset
        reset = 1;
        #15; // Hold reset for some time
        reset = 0;

        // Run the simulation for sufficient time to execute all instructions
        #1000; // Adjust the time as needed based on the program length
        $finish;
    end

    // Monitor key signals (optional)
    initial begin
        $monitor("Time: %0t | PC: %h | Instruction: %h | RegWrite: %b | ALUResult: %h",
                 $time, uut.pc_out, uut.instruction, uut.reg_write, uut.alu_result);
    end

    // Dump waveforms (optional)
    initial begin
        $dumpfile("risc_v_processor_tb.vcd");
        $dumpvars(0, risc_v_processor_tb);
    end

    // Monitoring register file contents
    wire [31:0] reg_file [0:31];
    integer i;

    // Access the register file inside the processor for monitoring
    generate
        genvar idx;
        for (idx = 0; idx < 32; idx = idx + 1) begin : reg_monitor
            assign reg_file[idx] = uut.RF.registers[idx];
        end
    endgenerate

    // Display register values at the end of simulation
    initial begin
        #1010; // Wait until simulation ends
        $display("\nRegister File Contents at the End of Simulation:");
        for (i = 0; i < 32; i = i + 1) begin
            $display("x%0d = %h", i, reg_file[i]);
        end
    end

    // Optionally monitor data memory contents if needed
    // (Not necessary in this test, as we are focusing on registers)

endmodule

RISC_V.sim/sim_1/behav/xsim/risc_v_processor_tb.vcd
$date
   Mon Oct 21 01:04:18 2024
$end

$version
  2023.2
  $dumpfile ("risc_v_processor_tb.vcd") 
$end

$timescale
  1ps
$end

$scope module risc_v_processor_tb $end
$var reg 1 ! clk $end
$var reg 1 " reset $end
$var integer 32 # i [31:0] $end
$scope module uut $end
$var wire 1 $ clk $end
$var wire 1 % reset $end
$var wire 32 & pc_in [31:0] $end
$var wire 32 ' pc_out [31:0] $end
$var wire 32 ( instruction [31:0] $end
$var wire 32 ) rs1_data [31:0] $end
$var wire 32 * rs2_data [31:0] $end
$var wire 32 + alu_result [31:0] $end
$var wire 32 , mem_read_data [31:0] $end
$var wire 32 - write_data [31:0] $end
$var wire 32 . immediate [31:0] $end
$var wire 1 / zero $end
$var wire 7 0 opcode [6:0] $end
$var wire 3 1 funct3 [2:0] $end
$var wire 7 2 funct7 [6:0] $end
$var wire 5 3 rs1_addr [4:0] $end
$var wire 5 4 rs2_addr [4:0] $end
$var wire 5 5 rd_addr [4:0] $end
$var wire 1 6 reg_write $end
$var wire 1 7 mem_to_reg $end
$var wire 1 8 mem_read $end
$var wire 1 9 mem_write $end
$var wire 1 : branch $end
$var wire 1 ; alu_src $end
$var wire 2 < alu_op [1:0] $end
$var wire 4 = alu_control [3:0] $end
$var wire 32 > alu_operand_b [31:0] $end
$var wire 32 ? pc_plus_4 [31:0] $end
$var wire 32 @ branch_target [31:0] $end
$scope module PC $end
$var wire 1 $ clk $end
$var wire 1 % reset $end
$var wire 32 & pc_in [31:0] $end
$var reg 32 A pc_out [31:0] $end
$upscope $end
$scope module IMEM $end
$var wire 32 ' addr [31:0] $end
$var wire 32 ( instruction [31:0] $end
$var integer 32 B i [31:0] $end
$var reg 12 C imm [11:0] $end
$var reg 5 D rd [4:0] $end
$var reg 5 E rs1 [4:0] $end
$var reg 5 F rs2 [4:0] $end
$var reg 7 G funct7 [6:0] $end
$var reg 3 H funct3 [2:0] $end
$var reg 7 I opcode [6:0] $end
$var reg 32 J instruction_word [31:0] $end
$upscope $end
$scope module CU $end
$var wire 7 0 opcode [6:0] $end
$var reg 1 K reg_write $end
$var reg 1 L mem_to_reg $end
$var reg 1 M mem_read $end
$var reg 1 N mem_write $end
$var reg 1 O branch $end
$var reg 2 P alu_op [1:0] $end
$var reg 1 Q alu_src $end
$upscope $end
$scope module RF $end
$var wire 1 $ clk $end
$var wire 5 3 rs1_addr [4:0] $end
$var wire 5 4 rs2_addr [4:0] $end
$var wire 5 5 rd_addr [4:0] $end
$var wire 32 - rd_data [31:0] $end
$var wire 1 6 reg_write $end
$var wire 32 ) rs1_data [31:0] $end
$var wire 32 * rs2_data [31:0] $end
$var integer 32 R i [31:0] $end
$upscope $end
$scope module SE $end
$var wire 32 ( instruction [31:0] $end
$var reg 32 S immediate [31:0] $end
$upscope $end
$scope module ALU_CU $end
$var wire 2 < alu_op [1:0] $end
$var wire 3 1 funct3 [2:0] $end
$var wire 7 2 funct7 [6:0] $end
$var reg 4 T alu_control [3:0] $end
$upscope $end
$scope module ALU $end
$var wire 32 ) operand_a [31:0] $end
$var wire 32 > operand_b [31:0] $end
$var wire 4 = alu_control [3:0] $end
$var reg 32 U alu_result [31:0] $end
$var wire 1 / zero $end
$upscope $end
$scope module DMEM $end
$var wire 1 $ clk $end
$var wire 32 + addr [31:0] $end
$var wire 32 * write_data [31:0] $end
$var wire 1 9 mem_write $end
$var wire 1 8 mem_read $end
$var reg 32 V read_data [31:0] $end
$var integer 32 W i [31:0] $end
$upscope $end
$upscope $end
$upscope $end
$enddefinitions $end

#0
$dumpvars
0!
1"
bx #
0$
1%
b100 &
b0 '
b101000000000000010010011 (
b0 )
b0 *
b1010 +
b0 ,
b1010 -
b1010 .
0/
b10011 0
b0 1
b0 2
b0 3
b1010 4
b1 5
16
07
08
09
0:
1;
b0 <
b10 =
b1010 >
b100 ?
b1010 @
b0 A
b11111 B
b100110110 C
b11011 D
b1001 E
b1010 F
b0 G
b10 H
b110011 I
b101001001010110110110011 J
1K
0L
0M
0N
0O
b0 P
1Q
b100000 R
b1010 S
b10 T
b1010 U
b0 V
b100000000 W
$end

#5000
1!
1$

#10000
0!
0$

#15000
1!
0"
1$
0%
b1000 &
b100 '
b1010000000000000100010011 (
b10100 +
b10100 -
b10100 .
b10100 4
b10 5
b10100 >
b1000 ?
b11000 @
b100 A
b10100 S
b10100 U

#20000
0!
0$

#25000
1!
1$
b1100 &
b1000 '
b1111000000000000110010011 (
b11110 +
b11110 -
b11110 .
b11110 4
b11 5
b11110 >
b1100 ?
b100110 @
b1000 A
b11110 S
b11110 U

#30000
0!
0$

#35000
1!
1$
b10000 &
b1100 '
b10100000000000001000010011 (
b101000 +
b101000 -
b101000 .
b1 2
b1000 4
b100 5
b101000 >
b10000 ?
b110100 @
b1100 A
b101000 S
b101000 U

#40000
0!
0$

#45000
1!
1$
b10100 &
b10000 '
b11001000000000001010010011 (
b110010 +
b110010 -
b110010 .
b10010 4
b101 5
b110010 >
b10100 ?
b1000010 @
b10000 A
b110010 S
b110010 U

#50000
0!
0$

#55000
1!
1$
b11000 &
b10100 '
b11110000000000001100010011 (
b111100 +
b111100 -
b111100 .
b11100 4
b110 5
b111100 >
b11000 ?
b1010000 @
b10100 A
b111100 S
b111100 U

#60000
0!
0$

#65000
1!
1$
b11100 &
b11000 '
b100011000000000001110010011 (
b111100 *
b1000110 +
b1000110 -
b1000110 .
b10 2
b110 4
b111 5
b1000110 >
b11100 ?
b1011110 @
b11000 A
b1000110 S
b1000110 U

#70000
0!
0$

#75000
1!
1$
b100000 &
b11100 '
b101000000000000010000010011 (
b0 *
b1010000 +
b1010000 -
b1010000 .
b10000 4
b1000 5
b1010000 >
b100000 ?
b1101100 @
b11100 A
b1010000 S
b1010000 U

#80000
0!
0$

#85000
1!
1$
b100100 &
b100000 '
b101101000000000010010010011 (
b1011010 +
b1011010 -
b1011010 .
b11010 4
b1001 5
b1011010 >
b100100 ?
b1111010 @
b100000 A
b1011010 S
b1011010 U

#90000
0!
0$

#95000
1!
1$
b101000 &
b100100 '
b110010000000000010100010011 (
b101000 *
b1100100 +
b1100100 -
b1100100 .
b11 2
b100 4
b1010 5
b1100100 >
b101000 ?
b10001000 @
b100100 A
b1100100 S
b1100100 U

#100000
0!
0$

#105000
1!
1$
b101100 &
b101000 '
b110111000000000010110010011 (
b0 *
b1101110 +
b1101110 -
b1101110 .
b1110 4
b1011 5
b1101110 >
b101100 ?
b10010110 @
b101000 A
b1101110 S
b1101110 U

#110000
0!
0$

#115000
1!
1$
b110000 &
b101100 '
b111100000000000011000010011 (
b1111000 +
b1111000 -
b1111000 .
b11000 4
b1100 5
b1111000 >
b110000 ?
b10100100 @
b101100 A
b1111000 S
b1111000 U

#120000
0!
0$

#125000
1!
1$
b110100 &
b110000 '
b1000001000000000011010010011 (
b10100 *
b10000010 +
b10000010 -
b10000010 .
b100 2
b10 4
b1101 5
b10000010 >
b110100 ?
b10110010 @
b110000 A
b10000010 S
b10000010 U

#130000
0!
0$

#135000
1!
1$
b111000 &
b110100 '
b1000110000000000011100010011 (
b1111000 *
b10001100 +
b10001100 -
b10001100 .
b1100 4
b1110 5
b10001100 >
b111000 ?
b11000000 @
b110100 A
b10001100 S
b10001100 U

#140000
0!
0$

#145000
1!
1$
b111100 &
b111000 '
b1001011000000000011110010011 (
b0 *
b10010110 +
b10010110 -
b10010110 .
b10110 4
b1111 5
b10010110 >
b111100 ?
b11001110 @
b111000 A
b10010110 S
b10010110 U

#150000
0!
0$

#155000
1!
1$
b1000000 &
b111100 '
b1010000000000000100000010011 (
b10100000 +
b10100000 -
b10100000 .
b101 2
b0 4
b10000 5
b10100000 >
b1000000 ?
b11011100 @
b111100 A
b10100000 S
b10100000 U

#160000
0!
0$

#165000
1!
1$
b1000100 &
b1000000 '
b1010101000000000100010010011 (
b1100100 *
b10101010 +
b10101010 -
b10101010 .
b1010 4
b10001 5
b10101010 >
b1000100 ?
b11101010 @
b1000000 A
b10101010 S
b10101010 U

#170000
0!
0$

#175000
1!
1$
b1001000 &
b1000100 '
b1011010000000000100100010011 (
b0 *
b10110100 +
b10110100 -
b10110100 .
b10100 4
b10010 5
b10110100 >
b1001000 ?
b11111000 @
b1000100 A
b10110100 S
b10110100 U

#180000
0!
0$

#185000
1!
1$
b1001100 &
b1001000 '
b1011111000000000100110010011 (
b10111110 +
b10111110 -
b10111110 .
b11110 4
b10011 5
b10111110 >
b1001100 ?
b100000110 @
b1001000 A
b10111110 S
b10111110 U

#190000
0!
0$

#195000
1!
1$
b1010000 &
b1001100 '
b1100100000000000101000010011 (
b1010000 *
b11001000 +
b11001000 -
b11001000 .
b110 2
b1000 4
b10100 5
b11001000 >
b1010000 ?
b100010100 @
b1001100 A
b11001000 S
b11001000 U

#200000
0!
0$

#205000
1!
1$
b1010100 &
b1010000 '
b1101001000000000101010010011 (
b10110100 *
b11010010 +
b11010010 -
b11010010 .
b10010 4
b10101 5
b11010010 >
b1010100 ?
b100100010 @
b1010000 A
b11010010 S
b11010010 U

#210000
0!
0$

#215000
1!
1$
b1011000 &
b1010100 '
b1101110000000000101100010011 (
b0 *
b11011100 +
b11011100 -
b11011100 .
b11100 4
b10110 5
b11011100 >
b1011000 ?
b100110000 @
b1010100 A
b11011100 S
b11011100 U

#220000
0!
0$

#225000
1!
1$
b1011100 &
b1011000 '
b1110011000000000101110010011 (
b111100 *
b11100110 +
b11100110 -
b11100110 .
b111 2
b110 4
b10111 5
b11100110 >
b1011100 ?
b100111110 @
b1011000 A
b11100110 S
b11100110 U

#230000
0!
0$

#235000
1!
1$
b1100000 &
b1011100 '
b1111000000000000110000010011 (
b10100000 *
b11110000 +
b11110000 -
b11110000 .
b10000 4
b11000 5
b11110000 >
b1100000 ?
b101001100 @
b1011100 A
b11110000 S
b11110000 U

#240000
0!
0$

#245000
1!
1$
b1100100 &
b1100000 '
b1111101000000000110010010011 (
b0 *
b11111010 +
b11111010 -
b11111010 .
b11010 4
b11001 5
b11111010 >
b1100100 ?
b101011010 @
b1100000 A
b11111010 S
b11111010 U

#250000
0!
0$

#255000
1!
1$
b1101000 &
b1100100 '
b10000010000000000110100010011 (
b101000 *
b100000100 +
b100000100 -
b100000100 .
b1000 2
b100 4
b11010 5
b100000100 >
b1101000 ?
b101101000 @
b1100100 A
b100000100 S
b100000100 U

#260000
0!
0$

#265000
1!
1$
b1101100 &
b1101000 '
b10000111000000000110110010011 (
b10001100 *
b100001110 +
b100001110 -
b100001110 .
b1110 4
b11011 5
b100001110 >
b1101100 ?
b101110110 @
b1101000 A
b100001110 S
b100001110 U

#270000
0!
0$

#275000
1!
1$
b1110000 &
b1101100 '
b10001100000000000111000010011 (
b11110000 *
b100011000 +
b100011000 -
b100011000 .
b11000 4
b11100 5
b100011000 >
b1110000 ?
b110000100 @
b1101100 A
b100011000 S
b100011000 U

#280000
0!
0$

#285000
1!
1$
b1110100 &
b1110000 '
b10010001000000000111010010011 (
b10100 *
b100100010 +
b100100010 -
b100100010 .
b1001 2
b10 4
b11101 5
b100100010 >
b1110100 ?
b110010010 @
b1110000 A
b100100010 S
b100100010 U

#290000
0!
0$

#295000
1!
1$
b1111000 &
b1110100 '
b10010110000000000111100010011 (
b1111000 *
b100101100 +
b100101100 -
b100101100 .
b1100 4
b11110 5
b100101100 >
b1111000 ?
b110100000 @
b1110100 A
b100101100 S
b100101100 U

#300000
0!
0$

#305000
1!
1$
b1111100 &
b1111000 '
b10011011000000000111110010011 (
b11011100 *
b100110110 +
b100110110 -
b100110110 .
b10110 4
b11111 5
b100110110 >
b1111100 ?
b110101110 @
b1111000 A
b100110110 S
b100110110 U

#310000
0!
0$

#315000
1!
1$
b10000000 &
b1111100 '
b1000001000111110110011 (
b1010 )
b10100 *
b11110 +
b11110 -
b0 .
b110011 0
b0 2
b1 3
b10 4
0;
b10 <
b10100 >
b10000000 ?
b1111100 @
b1111100 A
b10 P
0Q
b0 S
b11110 U

#320000
0!
0$

#325000
1!
1$
b10000100 &
b10000000 '
b1000000010000011000111100110011 (
b11110 )
b101000 *
b11111111111111111111111111110110 +
b11111111111111111111111111110110 -
b100000 2
b11 3
b100 4
b11110 5
b110 =
b101000 >
b10000100 ?
b10000000 @
b10000000 A
b110 T
b11111111111111111111111111110110 U

#330000
0!
0$

#335000
1!
1$
b10001000 &
b10000100 '
b11000101111111010110011 (
b110010 )
b111100 *
b110000 +
b110000 -
b111 1
b0 2
b101 3
b110 4
b11101 5
b0 =
b111100 >
b10001000 ?
b10000100 @
b10000100 A
b0 T
b110000 U

#340000
0!
0$

#345000
1!
1$
b10001100 &
b10001000 '
b100000111110111000110011 (
b1000110 )
b1010000 *
b1010110 +
b1010110 -
b110 1
b111 3
b1000 4
b11100 5
b1 =
b1010000 >
b10001100 ?
b10001000 @
b10001000 A
b1 T
b1010110 U

#350000
0!
0$

#355000
1!
1$
b10010000 &
b10001100 '
b101001001010110110110011 (
b1011010 )
b1100100 *
b1000000 +
b1000000 -
b10 1
b1001 3
b1010 4
b11011 5
b0 =
b1100100 >
b10010000 ?
b10001100 @
b10001100 A
b0 T
b1000000 U

#360000
0!
0$

#365000
1!
1$
b10010100 &
b10010000 '
bx (
bx )
bx *
bx +
bx -
x/
bx 0
bx 1
bx 2
bx 3
bx 4
bx 5
06
b0 <
b10 =
bx >
b10010100 ?
b10010000 @
b10010000 A
0K
b0 P
b10 T
bx U

#370000
0!
0$

#375000
1!
1$
b10011000 &
b10010100 '
b10011000 ?
b10010100 @
b10010100 A

#380000
0!
0$

#385000
1!
1$
b10011100 &
b10011000 '
b10011100 ?
b10011000 @
b10011000 A

#390000
0!
0$

#395000
1!
1$
b10100000 &
b10011100 '
b10100000 ?
b10011100 @
b10011100 A

#400000
0!
0$

#405000
1!
1$
b10100100 &
b10100000 '
b10100100 ?
b10100000 @
b10100000 A

#410000
0!
0$

#415000
1!
1$
b10101000 &
b10100100 '
b10101000 ?
b10100100 @
b10100100 A

#420000
0!
0$

#425000
1!
1$
b10101100 &
b10101000 '
b10101100 ?
b10101000 @
b10101000 A

#430000
0!
0$

#435000
1!
1$
b10110000 &
b10101100 '
b10110000 ?
b10101100 @
b10101100 A

#440000
0!
0$

#445000
1!
1$
b10110100 &
b10110000 '
b10110100 ?
b10110000 @
b10110000 A

#450000
0!
0$

#455000
1!
1$
b10111000 &
b10110100 '
b10111000 ?
b10110100 @
b10110100 A

#460000
0!
0$

#465000
1!
1$
b10111100 &
b10111000 '
b10111100 ?
b10111000 @
b10111000 A

#470000
0!
0$

#475000
1!
1$
b11000000 &
b10111100 '
b11000000 ?
b10111100 @
b10111100 A

#480000
0!
0$

#485000
1!
1$
b11000100 &
b11000000 '
b11000100 ?
b11000000 @
b11000000 A

#490000
0!
0$

#495000
1!
1$
b11001000 &
b11000100 '
b11001000 ?
b11000100 @
b11000100 A

#500000
0!
0$

#505000
1!
1$
b11001100 &
b11001000 '
b11001100 ?
b11001000 @
b11001000 A

#510000
0!
0$

#515000
1!
1$
b11010000 &
b11001100 '
b11010000 ?
b11001100 @
b11001100 A

#520000
0!
0$

#525000
1!
1$
b11010100 &
b11010000 '
b11010100 ?
b11010000 @
b11010000 A

#530000
0!
0$

#535000
1!
1$
b11011000 &
b11010100 '
b11011000 ?
b11010100 @
b11010100 A

#540000
0!
0$

#545000
1!
1$
b11011100 &
b11011000 '
b11011100 ?
b11011000 @
b11011000 A

#550000
0!
0$

#555000
1!
1$
b11100000 &
b11011100 '
b11100000 ?
b11011100 @
b11011100 A

#560000
0!
0$

#565000
1!
1$
b11100100 &
b11100000 '
b11100100 ?
b11100000 @
b11100000 A

#570000
0!
0$

#575000
1!
1$
b11101000 &
b11100100 '
b11101000 ?
b11100100 @
b11100100 A

#580000
0!
0$

#585000
1!
1$
b11101100 &
b11101000 '
b11101100 ?
b11101000 @
b11101000 A

#590000
0!
0$

#595000
1!
1$
b11110000 &
b11101100 '
b11110000 ?
b11101100 @
b11101100 A

#600000
0!
0$

#605000
1!
1$
b11110100 &
b11110000 '
b11110100 ?
b11110000 @
b11110000 A

#610000
0!
0$

#615000
1!
1$
b11111000 &
b11110100 '
b11111000 ?
b11110100 @
b11110100 A

#620000
0!
0$

#625000
1!
1$
b11111100 &
b11111000 '
b11111100 ?
b11111000 @
b11111000 A

#630000
0!
0$

#635000
1!
1$
b100000000 &
b11111100 '
b100000000 ?
b11111100 @
b11111100 A

#640000
0!
0$

#645000
1!
1$
b100000100 &
b100000000 '
b100000100 ?
b100000000 @
b100000000 A

#650000
0!
0$

#655000
1!
1$
b100001000 &
b100000100 '
b100001000 ?
b100000100 @
b100000100 A

#660000
0!
0$

#665000
1!
1$
b100001100 &
b100001000 '
b100001100 ?
b100001000 @
b100001000 A

#670000
0!
0$

